kibana_ql/__init__.py
kibana_ql/kql.parsimonious
kibana_ql/kql.py
kibana_ql/py.typed
kibana_ql-0.2.dist-info/LICENSE
kibana_ql-0.2.dist-info/WHEEL
kibana_ql-0.2.dist-info/METADATA
kibana_ql-0.2.dist-info/RECORD
