Metadata-Version: 2.1
Name: kibana_ql
Version: 0.2
Summary: Package to parse Kibana Query Language (KQL) strings. 
Author-email: Dobatymo <Dobatymo@users.noreply.github.com>
Requires-Python: >=3.7
Classifier: License :: OSI Approved :: MIT License
Requires-Dist: genutility[string]
Requires-Dist: parsimonious
Project-URL: Source, https://github.com/Dobatymo/kibana-ql-python
